pge/__init__.py
pge/add/__init__.py
pge/add/corr.py
pge/cluster/__init__.py
pge/cluster/centrality.py
pge/cluster/connect.py
pge/cluster/cycle.py
pge/cluster/leader.py
pge/cluster/modularity.py
pge/cluster/clustering/__init__.py
pge/cluster/clustering/clustering.py
pge/cluster/clustering/stationary.py
pge/init/__init__.py
pge/init/add.py
pge/init/creator.py
pge/init/custom_creator.py
pge/init/classes/__init__.py
pge/init/classes/graph.py
pge/model/__init__.py
pge/model/disease/__init__.py
pge/model/disease/node-based/ControlSpreading.py
pge/model/disease/node-based/SI2SD.py
pge/model/disease/node-based/SISD.py
pge/model/disease/node-based/UnconrolSpreading.py
pge/model/disease/node-based/__init__.py
pge/model/disease/node-based/basic.py
pge/model/growth/__init__.py
pge/model/growth/classification.py
pge/model/growth/created.py
pge/model/growth/bsc/__init__.py
pge/model/growth/bsc/basic.py
pge/model/growth/bsc/basic_fix.py
pge/model/growth/bsc/ca.py
pge/model/growth/bsc/delete.py
pge/model/growth/bsc/init.py
pge/model/growth/bsc/pa.py
pge/model/growth/bsc/pa_back.py
pge/model/growth/bsc/simple.py
pge/model/spreading/__init__.py
pge/model/spreading/time.py
pge/model/spreading/spreader/__init__.py
pge/model/spreading/spreader/basic.py
pge/model/spreading/spreader/burst.py
pge/model/spreading/spreader/fix_size.py
pge/model/spreading/spreader/uniform.py
pge/model/spreading/spreader/with_growth.py
pge/model/spreading/timer/__init__.py
pge/model/spreading/timer/poisson.py
pge/model/spreading/timer/simple.py
pge/ranks/__init__.py
pge/ranks/extrem_onl.py
pge/ranks/rank.py
pge/ranks/sliding.py
pge/ranks/onlcore/__init__.py
pge/ranks/onlcore/circle.py
pge/ranks/onlcore/dependence.py
pge/ranks/onlcore/gravity.py
pge/ranks/onlcore/line.py
pge/ranks/onlcore/way.py
pge/ranks/onlcore/criterion/__init__.py
pge/ranks/onlcore/criterion/rcriterion.py
pge/samples/__init__.py
pge/samples/networks/__init__.py
pge/viz/__init__.py
pge/viz/din_graph.py
pge/wlk/__init__.py
pge/wlk/rjw.py
pge-1.0.12.0.dist-info/LICENSE
pge-1.0.12.0.dist-info/METADATA
pge-1.0.12.0.dist-info/WHEEL
pge-1.0.12.0.dist-info/top_level.txt
pge-1.0.12.0.dist-info/RECORD
