Metadata-Version: 2.1
Name: pge
Version: 1.0.12.0
Summary: Graph modeling, EI estimation and analysis
Home-page: https://gitlab.com/BoBeni/PGEstimate
Author: Maxim Ryzhov
Author-email: ryzhov@phystech.edu
License: MIT
Platform: UNKNOWN
License-File: LICENSE
Requires-Dist: numpy
Requires-Dist: scipy
Requires-Dist: networkx
Requires-Dist: pandas
Requires-Dist: mcg
